{
  "id": "lich",
  "name": "リッチ",
  "hp": 35,
  "power": 15,
  "skill": 18,
  "mp": 60,
  "physical_resistance": 3,
  "magic_resistance": 20,
  "defense": 1,
  "is_flying": false,
  "is_undead": true,
  "attack_type": "magic",
  "attack_range": 5,
  "rank": "A",
  "instant_death_immune": true,
  "pre_delay": 0.7,
  "post_delay": 0.8,
  "chase_range": 8,
  "territory_range": 15,
  "behavior_description": "不死の大魔法使い。火と水の魔法弾を交互に放つ。魔法耐性が非常に高く、絶対に逃げない。MPが尽きると待機する。",
  "sprites": {
    "top": "res://assets/images/enemies/lich_top.png",
    "front": "res://assets/images/enemies/lich_front.png"
  }
}